README.md
setup.py
onederx/__init__.py
onederx/rest_api.py
onederx/websockets_api.py
onederx.egg-info/PKG-INFO
onederx.egg-info/SOURCES.txt
onederx.egg-info/dependency_links.txt
onederx.egg-info/requires.txt
onederx.egg-info/top_level.txt