Metadata-Version: 1.0
Name: onederx
Version: 0.0.4
Summary: REST and Websockets API for Onederx - Crypto derivatives exchange
Home-page: https://github.com/onederx/onederx-python
Author: Onederx
Author-email: UNKNOWN
License: MIT
Keywords: onederx,onederx-api,futures,derivative,leverage,client,api,trade,bitcoin,BTC,ethereum,ETH,wrapper,exchange,crypto,currency,trading,trading-api,memes
Platform: UNKNOWN
